{
    "Listings": [
        {
            "id": 1,
            "isbn": "2983520357035",
            "title": "Algorithms to Live By",
            "author": "Brian Christan",
            "edition": "1st",
            "notes": "Book is in good condition, used once. Great for any cognitive psychology classes.",
            "price": "50",
            "location": "Gainesville, FL"

        },
        {
            "id": 2,
            "isbn": "2983520357035",
            "title": "The Elegant Universe",
            "author": "Brian Christan",
            "edition": "1st",
            "notes": "Book is in good condition, used once. Great for any cognitive psychology classes.",
            "price": "50",
            "location": "Gainesville, FL"

        },
        {
            "id": 3,
            "isbn": "2983520357035",
            "title": "Algorithms to Live By",
            "author": "Brian Christan",
            "edition": "1st",
            "notes": "Book is in good condition, used once. Great for any cognitive psychology classes.",
            "price": "50",
            "location": "Gainesville, FL"

        },
        {
            "id": 4,
            "isbn": "2983520357035",
            "title": "Algorithms to Live By",
            "author": "Brian Christan",
            "edition": "1st",
            "notes": "Book is in good condition, used once. Great for any cognitive psychology classes.",
            "price": "50",
            "location": "Gainesville, FL"

        },
        {
            "id": 5,
            "isbn": "2983520357035",
            "title": "Algorithms to Live By",
            "author": "Brian Christan",
            "edition": "1st",
            "notes": "Book is in good condition, used once. Great for any cognitive psychology classes.",
            "price": "50",
            "location": "Gainesville, FL"

        },
        {
            "id": 6,
            "isbn": "2983520357035",
            "title": "Algorithms to Live By",
            "author": "Brian Christan",
            "edition": "1st",
            "notes": "Book is in good condition, used once. Great for any cognitive psychology classes.",
            "price": "50",
            "location": "Gainesville, FL"

        },
        {
            "id": 7,
            "isbn": "2983520357035",
            "title": "Algorithms to Live By",
            "author": "Brian Christan",
            "edition": "1st",
            "notes": "Book is in good condition, used once. Great for any cognitive psychology classes.",
            "price": "50",
            "location": "Gainesville, FL"

        },
        {
            "id": 8,
            "isbn": "2983520357035",
            "title": "Algorithms to Live By",
            "author": "Brian Christan",
            "edition": "1st",
            "notes": "Book is in good condition, used once. Great for any cognitive psychology classes.",
            "price": "50",
            "location": "Gainesville, FL"

        },
        {
            "id": 9,
            "isbn": "2983520357035",
            "title": "Algorithms to Live By",
            "author": "Brian Christan",
            "edition": "1st",
            "notes": "Book is in good condition, used once. Great for any cognitive psychology classes.",
            "price": "50",
            "location": "Gainesville, FL"

        }
    ]
}